README.md
setup.cfg
setup.py
hamamatsu/__init__.py
hamamatsu/dcam.py
hamamatsu/simulator.py
hamamatsu.egg-info/PKG-INFO
hamamatsu.egg-info/SOURCES.txt
hamamatsu.egg-info/dependency_links.txt
hamamatsu.egg-info/entry_points.txt
hamamatsu.egg-info/not-zip-safe
hamamatsu.egg-info/requires.txt
hamamatsu.egg-info/top_level.txt