Metadata-Version: 2.1
Name: hamamatsu
Version: 0.1.3
Summary: Python library to access Hamamatsu using DCAM or RemoteEX interface
Home-page: https://github.com/tiagocoutinho/hamamatsu
Author: Tiago Coutinho
Author-email: coutinhotiago@gmail.com
License: GNU General Public License v3
Keywords: hamamatsu,remoteex,dcam,lima,simulator
Platform: UNKNOWN
Classifier: Development Status :: 2 - Pre-Alpha
Classifier: Intended Audience :: Developers
Classifier: License :: OSI Approved :: GNU General Public License v3 (GPLv3)
Classifier: Natural Language :: English
Classifier: Programming Language :: Python :: 3.7
Classifier: Programming Language :: Python :: 3.8
Classifier: Programming Language :: Python :: 3.9
Requires-Python: >=3.7
Provides-Extra: simulator
Provides-Extra: lima
Provides-Extra: all
